{
    "ISBN": 9784297100025,
    "タイトル": "世界一わかりやすいDreamweaver操作とサイト制作の教科書CC対応",
    "サブタイトル": "",
    "著者": "中川正道,やのうまり絵(みま),トミー/智子",
    "出版社": "",
    "説明": "モノを作るためには道具を自分の身体のように使えることが大切です。デジタルなクリエイティブの世界でもそれは同じ。創造するためには、まず技術を身につけましょう。機能やツールの使い方の初歩の初歩からはじめて、読み終わるころにはしっかりと基礎力がついているように、本当に必要な技術を選んで15のレッスンを構成しました。",
    "言語": "ja",
    "ページ数": 287,
    "発売日": "",
    "レーベル": "",
    "値段": 2480,
    "画像URL": "http://books.google.com/books/content?id=X-VYvAEACAAJ&printsec=frontcover&img=1&zoom=1&source=gbs_api",
    "大分類": 9,
    "中分類": 6,
    "小分類": 1033
}