{
    "ISBN": 9784862463937,
    "タイトル": "スカルプターのための美術解剖学 2 表情編",
    "サブタイトル": "",
    "著者": "アルディス・ザリンス",
    "出版社": "ボーンデジタル",
    "説明": "キックスターター発の“スカルプターのための美術解剖学”の第二弾。人間の体を簡潔に解説した、もっとも使いやすい、アーティスト向け美術解剖学のガイドブックがここにあります。本書は、解剖学の最も難しい領域である人間の表情に焦点を当てています。表情を作るための頭部の主要な構造の要点を直接的かつ分かりやすいビジュアルで説明しています。美術を専攻する学生、モデラー、スカルプター、イラストレーターに、本書は実践的な基礎を提供します。これをベースに、アナトミーの知識をさらに積み重ねることができます。より手軽に、自信をもって描きたい、造形したいすべての人にお勧めします。",
    "言語": "jpn",
    "ページ数": "220",
    "発売日": "20170818",
    "レーベル": "",
    "値段": 7000,
    "画像URL": "http://books.google.com/books/content?id=zHEtswEACAAJ&printsec=frontcover&img=1&zoom=1&source=gbs_api",
    "大分類": 13,
    "中分類": 2,
    "小分類": 1388
}