{
    "ISBN": 9784407337297,
    "タイトル": "ＣＧリテラシー Ｐｈｏｔｏｓｈｏｐ＆ＩｌｌｕｓｔｒａｔｏｒＣＣ+ＣＳ６",
    "サブタイトル": "",
    "著者": "影山明俊,牧由紀子",
    "出版社": "実教出版",
    "説明": "PhotoshopおよびIllustratorのCCに対応したCG作成の入門書。CCを基本に説明を行うが、CS6で操作方法が異なる場合は、注釈を入れてCS6でも学習できるよう配慮。\n",
    "言語": "jpn",
    "ページ数": "320",
    "発売日": "20151110",
    "レーベル": "",
    "値段": 2800,
    "画像URL": "http://books.google.com/books/content?id=VM59jgEACAAJ&printsec=frontcover&img=1&zoom=1&source=gbs_api",
    "大分類": 12,
    "中分類": 1,
    "小分類": 681
}